odoo/addons/bank_statement_foreign_currency/README.rst
odoo/addons/bank_statement_foreign_currency/__init__.py
odoo/addons/bank_statement_foreign_currency/__manifest__.py
odoo/addons/bank_statement_foreign_currency/i18n/bank_statement_foreign_currency.pot
odoo/addons/bank_statement_foreign_currency/readme/CONTRIBUTORS.rst
odoo/addons/bank_statement_foreign_currency/readme/DESCRIPTION.rst
odoo/addons/bank_statement_foreign_currency/static/description/icon.png
odoo/addons/bank_statement_foreign_currency/static/description/index.html
odoo/addons/bank_statement_foreign_currency/views/account_view.xml
odoo12_addon_bank_statement_foreign_currency-12.0.1.0.0.99.dev5.dist-info/METADATA
odoo12_addon_bank_statement_foreign_currency-12.0.1.0.0.99.dev5.dist-info/WHEEL
odoo12_addon_bank_statement_foreign_currency-12.0.1.0.0.99.dev5.dist-info/top_level.txt
odoo12_addon_bank_statement_foreign_currency-12.0.1.0.0.99.dev5.dist-info/RECORD
